pyaerocom/__init__.py
pyaerocom/_logging.py
pyaerocom/_lowlevel_helpers.py
pyaerocom/_warnings.py
pyaerocom/aux_var_helpers.py
pyaerocom/climatology_config.py
pyaerocom/combine_vardata_ungridded.py
pyaerocom/config_reader.py
pyaerocom/dynamic_rec_array.py
pyaerocom/exceptions.py
pyaerocom/filter.py
pyaerocom/geodesy.py
pyaerocom/grid_io.py
pyaerocom/griddeddata.py
pyaerocom/griddeddata_container.py
pyaerocom/helpers.py
pyaerocom/helpers_landsea_masks.py
pyaerocom/logging.ini
pyaerocom/mathutils.py
pyaerocom/metastandards.py
pyaerocom/obs_io.py
pyaerocom/projection_information.py
pyaerocom/region.py
pyaerocom/region_defs.py
pyaerocom/stationdata.py
pyaerocom/time_resampler.py
pyaerocom/trends_engine.py
pyaerocom/trends_helpers.py
pyaerocom/ungridded_data_container.py
pyaerocom/ungridded_data_metadata.py
pyaerocom/ungriddeddata.py
pyaerocom/ungriddeddata_structured.py
pyaerocom/utils.py
pyaerocom/var_groups.py
pyaerocom/varcollection.py
pyaerocom/variable.py
pyaerocom/variable_helpers.py
pyaerocom/varnameinfo.py
pyaerocom/vert_coords.py
pyaerocom/vertical_profile.py
pyaerocom/aeroval/README.md
pyaerocom/aeroval/__init__.py
pyaerocom/aeroval/_processing_base.py
pyaerocom/aeroval/aux_io_helpers.py
pyaerocom/aeroval/bulkfraction_engine.py
pyaerocom/aeroval/coldatatojson_engine.py
pyaerocom/aeroval/coldatatojson_helpers.py
pyaerocom/aeroval/collections.py
pyaerocom/aeroval/exceptions.py
pyaerocom/aeroval/experiment_output.py
pyaerocom/aeroval/experiment_processor.py
pyaerocom/aeroval/fairmode_statistics.py
pyaerocom/aeroval/fairmode_stats.py
pyaerocom/aeroval/glob_defaults.py
pyaerocom/aeroval/helpers.py
pyaerocom/aeroval/json_utils.py
pyaerocom/aeroval/modelentry.py
pyaerocom/aeroval/modelmaps_engine.py
pyaerocom/aeroval/modelmaps_helpers.py
pyaerocom/aeroval/obsentry.py
pyaerocom/aeroval/superobs_engine.py
pyaerocom/aeroval/utils.py
pyaerocom/aeroval/varinfo_web.py
pyaerocom/aeroval/config/__init__.py
pyaerocom/aeroval/config/ciconfigs/__init__.py
pyaerocom-0.36.0.dist-info/entry_points.txt
pyaerocom-0.36.0.dist-info/licenses/LICENSE
pyaerocom-0.36.0.dist-info/WHEEL
pyaerocom-0.36.0.dist-info/METADATA
pyaerocom-0.36.0.dist-info/RECORD
