Metadata-Version: 2.4
Name: pyaerocom
Version: 0.36.0
Summary: pyaerocom model evaluation software
Author: MET Norway
Requires-Python: >=3.10
Classifier: Programming Language :: Python :: 3 :: Only
Classifier: Programming Language :: Python :: 3.10
Classifier: Programming Language :: Python :: 3.11
Classifier: Programming Language :: Python :: 3.12
Classifier: Programming Language :: Python :: 3.13
Classifier: License :: OSI Approved :: GNU Lesser General Public License v3 (LGPLv3)
Classifier: Operating System :: OS Independent
Classifier: Development Status :: 3 - Alpha
Classifier: Intended Audience :: Science/Research
Classifier: Intended Audience :: Education
Classifier: Topic :: Scientific/Engineering :: Atmospheric Science
License-File: LICENSE
Requires-Dist: aerovaldb>=0.5.0, < 0.6.0
Requires-Dist: scitools-iris>=3.11.0
Requires-Dist: xarray>=2022.12.0
Requires-Dist: cartopy>=0.21.1
Requires-Dist: matplotlib>=3.7.1
Requires-Dist: scipy>=1.10.1
Requires-Dist: pandas>=1.5.3
Requires-Dist: numpy>=1.25.0
Requires-Dist: seaborn>=0.12.2
Requires-Dist: dask
Requires-Dist: geonum==1.5.0
Requires-Dist: simplejson
Requires-Dist: requests
Requires-Dist: geocoder_reverse_natural_earth
Requires-Dist: tqdm
Requires-Dist: openpyxl
Requires-Dist: typer>=0.7.0
Requires-Dist: polars>=1.31.0
Requires-Dist: tomli>=2.0.1; python_version < "3.11"
Requires-Dist: importlib-resources>=5.10; python_version < "3.11"
Requires-Dist: typing-extensions>=4.6.1; python_version < "3.11"
Requires-Dist: cf-units>=3.3.0
Requires-Dist: pydantic~=2.7
Requires-Dist: pyproj>=3.0.0
Requires-Dist: pyaro>=0.2.0, <0.3.0
Requires-Dist: pooch>=1.7.0
Requires-Dist: psutil>=5.0.0
Requires-Dist: contourpy>=1.3.0
Requires-Dist: geojson
Requires-Dist: pytest-sugar ; extra == "dev"
Requires-Dist: pytest-xdist ; extra == "dev"
Requires-Dist: pre-commit ; extra == "dev"
Requires-Dist: pytest-mock ; extra == "dev"
Requires-Dist: sphinx>=7.2.6 ; extra == "docs"
Requires-Dist: sphinxcontrib-napoleon ; extra == "docs"
Requires-Dist: sphinx_rtd_theme ; extra == "docs"
Requires-Dist: sphinx-argparse ; extra == "docs"
Requires-Dist: nbsphinx ; extra == "docs"
Requires-Dist: snowballstemmer<3 ; extra == "docs"
Requires-Dist: mypy>=1.5.1 ; extra == "lint"
Requires-Dist: types-requests ; extra == "lint"
Requires-Dist: types-setuptools ; extra == "lint"
Requires-Dist: types-simplejson ; extra == "lint"
Requires-Dist: pytest>=7.4 ; extra == "test"
Requires-Dist: pytest-dependency ; extra == "test"
Requires-Dist: pytest-cov ; extra == "test"
Requires-Dist: packaging ; extra == "test"
Requires-Dist: pytest-xdist ; extra == "test"
Requires-Dist: pytest-mock ; extra == "test"
Requires-Dist: pyaro-readers ==0.1.5 ; extra == "test"
Project-URL: Bug Tracker, https://github.com/metno/pyaerocom/issues
Project-URL: Documentation, https://pyaerocom.readthedocs.io
Project-URL: Homepage, https://github.com/metno/pyaerocom
Project-URL: Source Code, https://github.com/metno/pyaerocom
Provides-Extra: dev
Provides-Extra: docs
Provides-Extra: lint
Provides-Extra: test
